setup.py
green_monkey/__init__.py
green_monkey/utils.py
green_monkey.egg-info/PKG-INFO
green_monkey.egg-info/SOURCES.txt
green_monkey.egg-info/dependency_links.txt
green_monkey.egg-info/not-zip-safe
green_monkey.egg-info/requires.txt
green_monkey.egg-info/top_level.txt