Metadata-Version: 1.0
Name: green-monkey
Version: 0.1.2
Summary: Use green versions of all possible modules
Home-page: http://github.com/philipn/green-monkey/
Author: Philip Neustrom
Author-email: philipn@gmail.com
License: UNKNOWN
Platform: UNKNOWN
Classifier: Development Status :: 3 - Alpha
Classifier: License :: OSI Approved :: BSD License
Classifier: Operating System :: OS Independent
Classifier: Programming Language :: Python
Classifier: Topic :: Internet
Classifier: Topic :: Software Development :: Libraries :: Python Modules
Classifier: Intended Audience :: Developers
